{
  "categories": [
    {
      "title": "热门教程",
      "projects": [
        {
          "title": "Python3 教程",
          "icon": "app.media.cover_python3",
          "description": "Python3.x版本，未来主流的版本。"
        },
        {
          "title": "Java 教程",
          "icon": "app.media.cover_java",
          "description": "一种可以撰写跨平台应用软件的面向对象的程序设计语言。"
        },
        {
          "title": "VUE3 教程",
          "icon": "app.media.cover_vue3course",
          "description": "Vue (读音 /vjuː/，类似于 view) 是一套用于构建用..."
        },
        {
          "title": "微信小程序开发文档",
          "icon": "app.media.cover_weixinapp",
          "description": "微信小程序开发文档，主要介绍了微信小程序的开发教程，微信小程序的a..."
        },
        {
          "title": "鸿蒙OS开发文档",
          "icon": "app.media.cover_harmonyos",
          "description": "华为自有开源操作系统鸿蒙OS，鸿蒙OS凭借多终端开发IDE，多语言..."
        },
        {
          "title": "HTML 教程",
          "icon": "app.media.cover_html",
          "description": "HTML 指超文本标记语言。 HTML 是通向 WEB 技术世界..."
        },
        {
          "title": "C语言教程",
          "icon": "app.media.cover_c",
          "description": "一门通用计算机编程语言"
        },
        {
          "title": "C++ 教程",
          "icon": "app.media.cover_cpp",
          "description": "C++是在C语言的基础上开发的一种通用编程语言。"
        },
        {
          "title": "Linux 教程",
          "icon": "app.media.cover_linux",
          "description": "Linux是一套免费使用和自由传播的类Unix操作系统。"
        },
        {
          "title": "SQL 教程",
          "icon": "app.media.cover_sql",
          "description": "SQL 是用于访问和处理数据库的标准的计算机语言。 在本教程中，您..."
        },
        {
          "title": "PHP 教程",
          "icon": "app.media.cover_php",
          "description": "PHP 是一种创建动态交互性站点的强有力的服务器端脚本语言。 P..."
        },
        {
          "title": "JavaScript 教程",
          "icon": "app.media.cover_javascript",
          "description": "JavaScript 是世界上最流行的脚本语言。 JavaScr..."
        }
      ]
    },
    {
      "title": "HTML/CSS",
      "projects": [
        {
          "title": "HTML 教程",
          "icon": "app.media.cover_html",
          "description": "HTML 指超文本标记语言。 HTML 是通向 WEB 技术世界..."
        },
        {
          "title": "XHTML 教程",
          "icon": "app.media.cover_xhtml",
          "description": "XHTML是一种比HTML更为严格的可扩展超文本标记语言，也是一种..."
        },
        {
          "title": "HTML5 教程",
          "icon": "app.media.cover_html5",
          "description": "HTML 5 是下一代的 HTML。 HTML5 仍处于完善之中..."
        },
        {
          "title": "HTML 参考手册",
          "icon": "app.media.cover_htmltags",
          "description": "您可以使用 HTML 来建立自己的 WEB 站点。 在本手册中，..."
        },
        {
          "title": "CSS 教程",
          "icon": "app.media.cover_css",
          "description": "CSS 指层叠样式表（Cascading Style Sheets..."
        },
        {
          "title": "CSS3 教程",
          "icon": "app.media.cover_css3",
          "description": "CSS3 是最新的 CSS 标准。 我们的 CSS3 教程向您讲..."
        },
        {
          "title": "CSS 参考手册",
          "icon": "app.media.cover_cssref",
          "description": "css的基础参考手册，通过一系列主流浏览器的测试，敬请放心阅读。"
        },
        {
          "title": "Less 教程",
          "icon": "app.media.cover_less",
          "description": "LESS是一个CSS预处理器，可以为网站启用可自定义，可管理和可重..."
        },
        {
          "title": "Sass 教程",
          "icon": "app.media.cover_sass",
          "description": "Sass是CSS预处理器之一，它能让你更好的、更轻松的工作。这个系..."
        }
      ]
    },
    {
      "title": "JavaScript",
      "projects": [
        {
          "title": "JavaScript 教程",
          "icon": "app.media.cover_javascript",
          "description": "JavaScript 是世界上最流行的脚本语言。 JavaScr..."
        },
        {
          "title": "HTML DOM 教程",
          "icon": "app.media.cover_htmldom",
          "description": "HTML DOM 定义了访问和操作 HTML 文档的标准方法。..."
        },
        {
          "title": "JavaScript 和 HTML DOM 参考手册",
          "icon": "app.media.cover_jsref",
          "description": "所有内置的JavaScript对象 所有浏览器对象 所有HTM..."
        },
        {
          "title": "JSON 教程",
          "icon": "app.media.cover_json",
          "description": "JSON：JavaScript 对象表示法（JavaScript..."
        },
        {
          "title": "AJAX 教程",
          "icon": "app.media.cover_ajax",
          "description": "AJAX = Asynchronous JavaScript an..."
        },
        {
          "title": "jQuery 教程",
          "icon": "app.media.cover_jquery",
          "description": "jQuery 是一个 JavaScript 库。 jQuery..."
        }
      ]
    }
  ]
}